lime_internal_getter/__init__.py
lime_internal_getter/interpolate.py
lime_internal_getter/main.py
lime_internal_getter/model.py
lime_internal_getter/parameters.py
lime_internal_getter/resistance.py
lime_internal_getter/soh.py
lime_internal_getter-0.3.2.dist-info/METADATA
lime_internal_getter-0.3.2.dist-info/WHEEL
lime_internal_getter-0.3.2.dist-info/RECORD
