Metadata-Version: 2.4
Name: lime_internal_getter
Version: 0.3.2
Summary: data handling library for Lime.ai
Project-URL: Homepage, https://gitlab.com/harisankar99/lime_internal_getter
Project-URL: Issues, https://gitlab.com/harisankar99/lime_internal_getter/issues
Author-email: Harisankar Suresh <harisankar.suresh@lime.ai>
Classifier: License :: OSI Approved :: MIT License
Classifier: Operating System :: OS Independent
Classifier: Programming Language :: Python :: 3
Requires-Python: >=3.8
Requires-Dist: fastparquet
Requires-Dist: pandas>=2.0.3
Requires-Dist: plotly
Requires-Dist: pyarrow
Requires-Dist: python-docx
Requires-Dist: requests
Requires-Dist: scikit-learn
Requires-Dist: scipy
Requires-Dist: tqdm
